{
    "safety_thresholds": {
        "max_temperature": 55.0,
        "min_temperature": -30.0,
        "max_temperature_jump": 3.0,
        "min_voltage": 250.0,
        "max_voltage": 450.0,
        "min_soc": 15.0,
        "critical_soh": 75.0,
        "max_current": 600.0
    },
    "ml_config": {
        "contamination": 0.05,
        "n_estimators": 250,
        "random_state": 42,
        "critical_score_threshold": -0.9,
        "warning_score_threshold": -0.6
    },
    "default_vin": "5YJ3E1EA8KF000001"
}